{
  "item_type": "Hoodie",
  "color": "Dark Grey",
  "brand": "Adidas",
  "size": "S",
  "material": "100% Cotton",
  "measurement_cm": "P2P: 50cm, Length: 69cm",
  "condition_notes": "Visible seam with loose threads",
  "image_type": null,
  "title": "Adidas Hoodie — Dark Grey",
  "images": [
    "20260309_190510.jpg",
    "20260309_190510.jpg",
    "20260309_190529.jpg",
    "20260309_190536.jpg",
    "20260309_190541.jpg",
    "20260309_190831.jpg",
    "20260309_190839.jpg",
    "20260309_190849.jpg"
  ],
  "image_types": [
    "FULL_FRONT_FLATLAY",
    "FULL_FRONT_FLATLAY",
    "DETAIL_SHOT",
    "DETAIL_SHOT",
    "DETAIL_SHOT",
    "DETAIL_SHOT",
    "DETAIL_SHOT",
    "DETAIL_SHOT"
  ],
  "image_captions": [
    "Dark grey hoodie with 'EVEN' logo on chest and Adidas logo on sleeve cuff.",
    "Dark grey hoodie with 'EVEN' logo on chest and Adidas logo on sleeve cuff.",
    "Back view showing white Adidas logo and Five Ten '10' logo on dark grey sweatpants.",
    "Close-up of grey hoodie showing white 'AVEN' logo with layered line design on chest. Neck tag visible at top.",
    "Neck tag reading adidas Size UK S US S F S I S CDN S/P MADE IN CHINA",
    "Vertical tape measure showing 69cm at the hem edge of dark grey sweatshirt material.",
    "Horizontal tape measure showing 50cm at the garment's edge.",
    "Neck tag showing '271' and '100% Cotton'. Care label reading '100% Cotton'. Visible seam with loose threads."
  ],
  "batch_index": 18,
  "processed_at": "2026-03-23T18:54:13.978398",
  "output_folder": "./vendora_ready\\Adidas_Hoodie_—_Dark_Grey_018",
  "condition": "Good",
  "enhanced_description": "Adidas EVEN Hoodie — Dark Grey\nBrand: Adidas\nSize: S (UK/US)\nCondition: Good\nComposition: 100% Cotton\nColor: Dark Grey\n\nMeasurements (Laid Flat):\nPit-to-Pit: 50cm\nLength: 69cm\n\nAbout the Piece\nA sleek, dark grey Adidas EVEN hoodie featuring a stylish layered line design on the chest. Crafted from premium 100% cotton for a soft, comfortable fit that layers perfectly with your everyday style.\n\nStyle Note: Streetwear / Minimalist Urban\n\nKey Detail\nThe hoodie showcases the iconic white 'AVEN' logo with its signature layered line graphic on the front, paired with an Adidas logo on the sleeve cuff. The garment is made in China and features a visible seam with loose threads near the neck tag area.\n\nSeller Notes\nShipping: 🚀 Next day shipping guaranteed!\n\nShop My Closet: Check out my other offers for more Adidas items—I'm happy to offer bundle discounts if you see something else you like!\n\nQuestions? Drop a comment or send an offer. I'm responsive and ready to ship.",
  "description": "Adidas EVEN Hoodie — Dark Grey\nBrand: Adidas\nSize: S (UK/US)\nCondition: Good\nComposition: 100% Cotton\nColor: Dark Grey\n\nMeasurements (Laid Flat):\nPit-to-Pit: 50cm\nLength: 69cm\n\nAbout the Piece\nA sleek, dark grey Adidas EVEN hoodie featuring a stylish layered line design on the chest. Crafted from premium 100% cotton for a soft, comfortable fit that layers perfectly with your everyday style.\n\nStyle Note: Streetwear / Minimalist Urban\n\nKey Detail\nThe hoodie showcases the iconic white 'AVEN' logo with its signature layered line graphic on the front, paired with an Adidas logo on the sleeve cuff. The garment is made in China and features a visible seam with loose threads near the neck tag area.\n\nSeller Notes\nShipping: 🚀 Next day shipping guaranteed!\n\nShop My Closet: Check out my other offers for more Adidas items—I'm happy to offer bundle discounts if you see something else you like!\n\nQuestions? Drop a comment or send an offer. I'm responsive and ready to ship."
}